telegram_webapp_auth/__init__.py
telegram_webapp_auth/auth.py
telegram_webapp_auth/data.py
telegram_webapp_auth/errors.py
telegram_webapp_auth-3.0.6.dist-info/LICENSE
telegram_webapp_auth-3.0.6.dist-info/METADATA
telegram_webapp_auth-3.0.6.dist-info/WHEEL
telegram_webapp_auth-3.0.6.dist-info/RECORD
