Metadata-Version: 2.1
Name: telegram-webapp-auth
Version: 3.0.6
Summary: Python package that implements Telegram Mini Apps authentication algorithms.
Home-page: https://pypi.org/project/telegram-webapp-auth/
License: MIT
Keywords: Telegram,Telegram Mini Apps,Telegram Bot,Poetry
Author: Dmitry Vasiliev
Author-email: contact.vasiliev.dmitry@gmail.com
Requires-Python: >=3.9.2,<4.0.0
Classifier: License :: OSI Approved :: MIT License
Classifier: Operating System :: OS Independent
Classifier: Programming Language :: Python :: 3
Classifier: Programming Language :: Python :: 3.10
Classifier: Programming Language :: Python :: 3.11
Classifier: Programming Language :: Python :: 3.12
Classifier: Programming Language :: Python :: 3.13
Classifier: Programming Language :: Python :: 3.9
Classifier: Topic :: Security
Requires-Dist: cryptography (>=44,<46)
Project-URL: Documentation, https://swimmwatch.github.io/telegram-webapp-auth/
Project-URL: Repository, https://github.com/swimmwatch/telegram-webapp-auth
